arxivory/__init__.py
arxivory/arxiv.py
arxivory/cohere.py
arxivory/commands/__init__.py
arxivory/commands/harvest.py
arxivory/commands/search.py
arxivory/constants.py
arxivory/main.py
arxivory-0.5.0.dist-info/WHEEL
arxivory-0.5.0.dist-info/entry_points.txt
arxivory-0.5.0.dist-info/METADATA
arxivory-0.5.0.dist-info/RECORD
