Metadata-Version: 2.3
Name: arxivory
Version: 0.5.0
Summary: A command-line tool for searching arXiv papers using natural language queries with semantic search powered by Cohere embeddings and reranking
Keywords: arxiv,search,semantic,papers,research,ai,nlp,cohere
Author: Rafid Al-Humaimidi
Author-email: Rafid Al-Humaimidi <rafidka@gmail.com>
License: MIT
Classifier: Development Status :: 4 - Beta
Classifier: Environment :: Console
Classifier: Intended Audience :: Developers
Classifier: Intended Audience :: Science/Research
Classifier: License :: OSI Approved :: MIT License
Classifier: Operating System :: OS Independent
Classifier: Programming Language :: Python :: 3
Classifier: Programming Language :: Python :: 3.12
Classifier: Topic :: Scientific/Engineering :: Information Analysis
Classifier: Topic :: Text Processing :: Linguistic
Classifier: Topic :: Utilities
Requires-Dist: typer>=0.9.0
Requires-Dist: cohere>=4.0.0
Requires-Dist: rich>=13.0.0
Requires-Dist: numpy>=1.24.0
Requires-Python: >=3.12
Project-URL: Documentation, https://github.com/rafidka/arxivory#readme
Project-URL: Homepage, https://github.com/rafidka/arxivory
Project-URL: Issues, https://github.com/rafidka/arxivory/issues
Project-URL: Repository, https://github.com/rafidka/arxivory
